lektor_tawk.py
lektor_tawk-0.1.dist-info/METADATA
lektor_tawk-0.1.dist-info/WHEEL
lektor_tawk-0.1.dist-info/entry_points.txt
lektor_tawk-0.1.dist-info/top_level.txt
lektor_tawk-0.1.dist-info/RECORD
