Metadata-Version: 2.1
Name: lektor-tawk
Version: 0.1
Summary: Lektor plugin to add Tawk to a website.
Home-page: https://github.com/F0liveira/Lektor-Tawk
Author: Fabio Oliveira
Author-email: lopesoliveirafabio@hotmail.com
License: MIT
Keywords: Lektor plugin
Platform: UNKNOWN
Classifier: Framework :: Lektor
Classifier: Environment :: Plugins
